turkeypy/__init__.py
turkeypy/__main__.py
turkeypy/compiler.py
turkeypy/vm.py
turkeypy-0.1.0.dist-info/entry_points.txt
turkeypy-0.1.0.dist-info/LICENSE
turkeypy-0.1.0.dist-info/METADATA
turkeypy-0.1.0.dist-info/WHEEL
turkeypy-0.1.0.dist-info/RECORD
